ade_cli/__init__.py
ade_cli/cli.py
ade_cli/compat.py
ade_cli/config.py
ade_cli/credentials.py
ade_cli/docker.py
ade_cli/dotenv.py
ade_cli/registry.py
ade_cli/utils.py
ade_cli-3.5.1.dist-info/LICENSE
ade_cli-3.5.1.dist-info/METADATA
ade_cli-3.5.1.dist-info/WHEEL
ade_cli-3.5.1.dist-info/entry_points.txt
ade_cli-3.5.1.dist-info/top_level.txt
ade_cli-3.5.1.dist-info/RECORD
