Metadata-Version: 2.1
Name: ade-cli
Version: 3.5.1
Summary: Agile Development Environment
Home-page: https://gitlab.com/ApexAI/ade-cli
Author: Ternaris
Author-email: team@ternaris.com
Maintainer: Apex.AI
Maintainer-email: tooling@apex.ai
License: Apache-2.0
Project-URL: Code, https://gitlab.com/ApexAI/ade-cli
Project-URL: Issue tracker, https://gitlab.com/ApexAI/ade-cli/issues
Platform: UNKNOWN
Requires-Python: >=3.5.2
Requires-Dist: cchardet
Requires-Dist: click (>=7.0)
Requires-Dist: aiodns
Requires-Dist: aiohttp (<3.5.0)
Requires-Dist: pdbpp
Provides-Extra: develop
Requires-Dist: Sphinx ; extra == 'develop'
Requires-Dist: sphinx-click ; extra == 'develop'
Requires-Dist: flake8 ; extra == 'develop'
Requires-Dist: flake8-formatter-junit-xml ; extra == 'develop'
Requires-Dist: pylint ; extra == 'develop'
Requires-Dist: pytest ; extra == 'develop'
Requires-Dist: pytest-cov ; extra == 'develop'
Requires-Dist: pytest-pylint ; extra == 'develop'
